setup.cfg
setup.py
mountebank/__init__.py
mountebank/mountebank.py
mountebank_python.egg-info/PKG-INFO
mountebank_python.egg-info/SOURCES.txt
mountebank_python.egg-info/dependency_links.txt
mountebank_python.egg-info/requires.txt
mountebank_python.egg-info/top_level.txt