Metadata-Version: 1.1
Name: mountebank-python
Version: 0.1.2
Summary: A thin convenience wrapper for interacting with Mountebank from Python
Home-page: https://github.com/aholyoke/mountebank-python
Author: Alex Holyoke
Author-email: aholyoke@uwaterloo.ca
License: MIT
Download-URL: https://github.com/aholyoke/mountebank-python/tarball/0.1
Keywords: testing,mountebank
Platform: UNKNOWN
